mufit/__init__.py
mufit/bulkglassfit.py
mufit/main.py
mufit-0.0.1.dist-info/licenses/LICENSE
mufit-0.0.1.dist-info/METADATA
mufit-0.0.1.dist-info/WHEEL
mufit-0.0.1.dist-info/entry_points.txt
mufit-0.0.1.dist-info/top_level.txt
mufit-0.0.1.dist-info/RECORD
