Metadata-Version: 2.4
Name: mufit
Version: 0.0.1
Summary: A small Solver
Author-email: Jeroen van t Ende <jeroen.vantende@outlook.com>
Project-URL: Homepage, https://github.com/Kwabratseur/fimufit
Classifier: Programming Language :: Python :: 3
Classifier: Operating System :: OS Independent
Classifier: License :: OSI Approved :: MIT License
Requires-Python: >=3.8
License-File: LICENSE
Requires-Dist: pandas
Requires-Dist: plotly
Requires-Dist: matplotlib
Requires-Dist: seaborn
Requires-Dist: scipy
Dynamic: license-file
